{
  "plugin": {
    "totalDownloads": 4,
    "stargazers": 0,
    "createdAt": "2025-11-04T09:18:15Z",
    "latestReleaseAt": "2025-11-06T18:05:19Z",
    "lastCommitDate": "2025-11-06T18:04:04Z",
    "commitCountInLast24Months": 5,
    "totalReleases": 2,
    "releases": [
      {
        "publishedAt": "2025-11-06T17:35:56Z",
        "downloads": 1
      },
      {
        "publishedAt": "2025-11-06T18:05:19Z",
        "downloads": 3
      }
    ],
    "openIssues": [],
    "closedIssues": [],
    "openPRs": [],
    "closedPRs": [],
    "mergedPRs": []
  },
  "now": "2026-03-04T01:30:56.848Z"
}