{
  "plugin": {
    "totalDownloads": 16,
    "stargazers": 1,
    "createdAt": "2026-02-19T19:59:05Z",
    "latestReleaseAt": "2026-02-20T01:06:32Z",
    "lastCommitDate": "2026-02-22T08:23:14Z",
    "commitCountInLast24Months": 24,
    "totalReleases": 4,
    "releases": [
      {
        "publishedAt": "2026-02-19T22:31:49Z",
        "downloads": 2
      },
      {
        "publishedAt": "2026-02-19T23:18:31Z",
        "downloads": 2
      },
      {
        "publishedAt": "2026-02-20T00:36:04Z",
        "downloads": 2
      },
      {
        "publishedAt": "2026-02-20T01:06:32Z",
        "downloads": 10
      }
    ],
    "openIssues": [],
    "closedIssues": [],
    "openPRs": [],
    "closedPRs": [],
    "mergedPRs": []
  },
  "now": "2026-03-04T01:06:30.795Z"
}