{
  "plugin": {
    "totalDownloads": 583,
    "stargazers": 2,
    "createdAt": "2024-09-19T00:36:13Z",
    "latestReleaseAt": "2024-09-19T03:53:17Z",
    "lastCommitDate": "2025-02-19T19:36:17Z",
    "commitCountInLast24Months": 12,
    "totalReleases": 2,
    "releases": [
      {
        "publishedAt": "2024-09-19T00:39:30Z",
        "downloads": 9
      },
      {
        "publishedAt": "2024-09-19T03:53:17Z",
        "downloads": 574
      }
    ],
    "openIssues": [],
    "closedIssues": [],
    "openPRs": [],
    "closedPRs": [],
    "mergedPRs": []
  },
  "now": "2026-03-04T02:25:56.926Z"
}