{
  "plugin": {
    "totalDownloads": 866,
    "stargazers": 109,
    "createdAt": "2024-02-06T23:39:50Z",
    "latestReleaseAt": "2024-06-22T17:16:57Z",
    "lastCommitDate": "2024-09-24T15:26:31Z",
    "commitCountInLast24Months": 20,
    "totalReleases": 4,
    "releases": [
      {
        "publishedAt": "2024-05-18T20:31:59Z",
        "downloads": 10
      },
      {
        "publishedAt": "2024-05-18T20:45:11Z",
        "downloads": 10
      },
      {
        "publishedAt": "2024-05-18T20:47:10Z",
        "downloads": 781
      },
      {
        "publishedAt": "2024-06-22T17:16:57Z",
        "downloads": 65
      }
    ],
    "openIssues": [
      {
        "label": "bug",
        "createdAt": "2024-03-11T14:57:49Z"
      },
      {
        "label": "bug",
        "createdAt": "2024-05-18T20:55:20Z"
      },
      {
        "label": "bug",
        "createdAt": "2024-05-20T10:09:12Z"
      },
      {
        "label": "bug",
        "createdAt": "2024-05-29T13:02:19Z"
      },
      {
        "label": "bug",
        "createdAt": "2024-06-04T13:41:33Z"
      },
      {
        "label": "bug",
        "createdAt": "2024-06-11T16:34:32Z"
      },
      {
        "label": "bug",
        "createdAt": "2024-06-22T17:07:49Z"
      },
      {
        "label": "bug",
        "createdAt": "2024-06-22T17:14:53Z"
      },
      {
        "label": "bug",
        "createdAt": "2026-01-08T20:58:41Z"
      }
    ],
    "closedIssues": [
      {
        "originalLabel": "bug",
        "reason": "completed",
        "createdAt": "2024-03-11T14:54:20Z",
        "closedAt": "2024-03-11T14:56:07Z"
      },
      {
        "originalLabel": "bug",
        "reason": "completed",
        "createdAt": "2024-03-11T14:54:30Z",
        "closedAt": "2024-05-18T20:54:42Z"
      },
      {
        "originalLabel": "bug",
        "reason": "completed",
        "createdAt": "2024-03-11T14:54:35Z",
        "closedAt": "2024-06-05T12:22:30Z"
      },
      {
        "originalLabel": "bug",
        "reason": "completed",
        "createdAt": "2024-03-11T14:55:47Z",
        "closedAt": "2024-05-18T20:54:31Z"
      },
      {
        "originalLabel": "bug",
        "reason": "completed",
        "createdAt": "2024-03-11T14:57:36Z",
        "closedAt": "2024-06-02T19:52:35Z"
      },
      {
        "originalLabel": "bug",
        "reason": "completed",
        "createdAt": "2024-05-31T16:30:27Z",
        "closedAt": "2024-06-10T18:40:24Z"
      },
      {
        "originalLabel": "bug",
        "reason": "completed",
        "createdAt": "2024-06-14T19:19:22Z",
        "closedAt": "2024-06-22T16:39:29Z"
      }
    ],
    "openPRs": [],
    "closedPRs": [
      {
        "createdAt": "2024-06-17T07:01:50Z",
        "closedAt": "2024-06-24T05:58:55Z"
      }
    ],
    "mergedPRs": []
  },
  "now": "2026-03-04T02:21:46.512Z"
}