{
  "plugin": {
    "totalDownloads": 922,
    "stargazers": 9,
    "createdAt": "2023-12-19T18:38:03Z",
    "latestReleaseAt": "2024-04-26T17:04:35Z",
    "lastCommitDate": "2024-11-15T19:14:12Z",
    "commitCountInLast24Months": 34,
    "totalReleases": 7,
    "releases": [
      {
        "publishedAt": "2024-03-07T14:53:21Z",
        "downloads": 6
      },
      {
        "publishedAt": "2024-03-07T16:05:58Z",
        "downloads": 6
      },
      {
        "publishedAt": "2024-03-07T16:11:01Z",
        "downloads": 6
      },
      {
        "publishedAt": "2024-03-08T11:19:19Z",
        "downloads": 6
      },
      {
        "publishedAt": "2024-03-13T19:47:41Z",
        "downloads": 7
      },
      {
        "publishedAt": "2024-04-14T04:32:54Z",
        "downloads": 168
      },
      {
        "publishedAt": "2024-04-26T17:04:35Z",
        "downloads": 723
      }
    ],
    "openIssues": [],
    "closedIssues": [
      {
        "originalLabel": "bug",
        "reason": "completed",
        "createdAt": "2024-04-18T08:38:25Z",
        "closedAt": "2024-04-18T12:00:47Z"
      },
      {
        "originalLabel": "bug",
        "reason": "completed",
        "createdAt": "2024-04-19T12:18:18Z",
        "closedAt": "2024-04-22T12:00:49Z"
      }
    ],
    "openPRs": [],
    "closedPRs": [],
    "mergedPRs": []
  },
  "now": "2026-03-04T02:20:13.147Z"
}