{
  "plugin": {
    "totalDownloads": 8229,
    "stargazers": 74,
    "createdAt": "2022-10-02T10:17:55Z",
    "latestReleaseAt": "2025-12-05T09:43:28Z",
    "lastCommitDate": "2026-02-12T06:30:38Z",
    "commitCountInLast24Months": 215,
    "totalReleases": 58,
    "releases": [
      {
        "publishedAt": "2024-03-15T03:33:27Z",
        "downloads": 39
      },
      {
        "publishedAt": "2024-04-18T02:48:59Z",
        "downloads": 3
      },
      {
        "publishedAt": "2024-04-19T08:55:39Z",
        "downloads": 6
      },
      {
        "publishedAt": "2024-04-29T07:54:09Z",
        "downloads": 4
      },
      {
        "publishedAt": "2024-05-01T04:27:39Z",
        "downloads": 6
      },
      {
        "publishedAt": "2024-05-02T03:33:35Z",
        "downloads": 209
      },
      {
        "publishedAt": "2024-05-10T03:28:45Z",
        "downloads": 4
      },
      {
        "publishedAt": "2024-05-10T11:19:18Z",
        "downloads": 56
      },
      {
        "publishedAt": "2024-05-13T03:56:29Z",
        "downloads": 18
      },
      {
        "publishedAt": "2024-05-13T13:35:34Z",
        "downloads": 74
      },
      {
        "publishedAt": "2024-05-16T08:39:20Z",
        "downloads": 62
      },
      {
        "publishedAt": "2024-05-19T08:48:45Z",
        "downloads": 101
      },
      {
        "publishedAt": "2024-05-26T04:23:05Z",
        "downloads": 90
      },
      {
        "publishedAt": "2024-06-01T08:30:39Z",
        "downloads": 72
      },
      {
        "publishedAt": "2024-06-04T10:45:08Z",
        "downloads": 93
      },
      {
        "publishedAt": "2024-06-10T11:05:59Z",
        "downloads": 86
      },
      {
        "publishedAt": "2024-06-15T01:55:55Z",
        "downloads": 99
      },
      {
        "publishedAt": "2024-06-22T14:31:23Z",
        "downloads": 94
      },
      {
        "publishedAt": "2024-06-28T07:42:22Z",
        "downloads": 100
      },
      {
        "publishedAt": "2024-07-06T10:13:31Z",
        "downloads": 111
      },
      {
        "publishedAt": "2024-07-13T15:42:05Z",
        "downloads": 5
      },
      {
        "publishedAt": "2024-07-13T16:09:47Z",
        "downloads": 110
      },
      {
        "publishedAt": "2024-07-21T09:53:04Z",
        "downloads": 575
      },
      {
        "publishedAt": "2024-10-12T07:44:44Z",
        "downloads": 273
      },
      {
        "publishedAt": "2024-11-02T09:31:08Z",
        "downloads": 317
      },
      {
        "publishedAt": "2024-11-30T14:14:16Z",
        "downloads": 31
      },
      {
        "publishedAt": "2024-12-01T07:40:51Z",
        "downloads": 113
      },
      {
        "publishedAt": "2024-12-07T02:43:47Z",
        "downloads": 387
      },
      {
        "publishedAt": "2025-01-14T06:53:29Z",
        "downloads": 124
      },
      {
        "publishedAt": "2025-01-20T12:07:34Z",
        "downloads": 234
      },
      {
        "publishedAt": "2025-02-07T08:57:11Z",
        "downloads": 37
      },
      {
        "publishedAt": "2025-02-08T02:00:37Z",
        "downloads": 67
      },
      {
        "publishedAt": "2025-02-10T03:47:16Z",
        "downloads": 4
      },
      {
        "publishedAt": "2025-02-10T03:56:13Z",
        "downloads": 163
      },
      {
        "publishedAt": "2025-02-18T06:29:51Z",
        "downloads": 5
      },
      {
        "publishedAt": "2025-02-18T06:37:56Z",
        "downloads": 8
      },
      {
        "publishedAt": "2025-02-18T08:14:51Z",
        "downloads": 45
      },
      {
        "publishedAt": "2025-02-19T08:55:29Z",
        "downloads": 6
      },
      {
        "publishedAt": "2025-02-19T09:03:06Z",
        "downloads": 5
      },
      {
        "publishedAt": "2025-02-19T09:07:23Z",
        "downloads": 306
      },
      {
        "publishedAt": "2025-03-17T12:16:31Z",
        "downloads": 53
      },
      {
        "publishedAt": "2025-03-19T09:20:06Z",
        "downloads": 3
      },
      {
        "publishedAt": "2025-03-19T09:22:02Z",
        "downloads": 62
      },
      {
        "publishedAt": "2025-03-20T12:59:27Z",
        "downloads": 136
      },
      {
        "publishedAt": "2025-03-26T11:12:08Z",
        "downloads": 170
      },
      {
        "publishedAt": "2025-04-04T07:04:59Z",
        "downloads": 149
      },
      {
        "publishedAt": "2025-04-11T15:53:41Z",
        "downloads": 141
      },
      {
        "publishedAt": "2025-04-17T12:31:03Z",
        "downloads": 1212
      },
      {
        "publishedAt": "2025-09-26T08:04:42Z",
        "downloads": 63
      },
      {
        "publishedAt": "2025-09-28T02:43:24Z",
        "downloads": 80
      },
      {
        "publishedAt": "2025-09-30T05:37:17Z",
        "downloads": 222
      },
      {
        "publishedAt": "2025-10-12T14:17:02Z",
        "downloads": 267
      },
      {
        "publishedAt": "2025-10-26T13:13:41Z",
        "downloads": 55
      },
      {
        "publishedAt": "2025-10-27T10:40:37Z",
        "downloads": 47
      },
      {
        "publishedAt": "2025-10-28T10:34:01Z",
        "downloads": 128
      },
      {
        "publishedAt": "2025-11-03T02:58:46Z",
        "downloads": 105
      },
      {
        "publishedAt": "2025-11-06T15:27:53Z",
        "downloads": 380
      },
      {
        "publishedAt": "2025-12-05T09:43:28Z",
        "downloads": 814
      }
    ],
    "openIssues": [
      {
        "label": "bug",
        "createdAt": "2024-09-05T11:46:08Z"
      },
      {
        "label": "bug",
        "createdAt": "2024-10-31T07:07:21Z"
      },
      {
        "label": "bug",
        "createdAt": "2024-11-16T17:33:31Z"
      },
      {
        "label": "bug",
        "createdAt": "2024-12-09T13:48:59Z"
      },
      {
        "label": "bug",
        "createdAt": "2025-02-08T03:21:43Z"
      },
      {
        "label": "bug",
        "createdAt": "2025-02-25T08:17:00Z"
      },
      {
        "label": "bug",
        "createdAt": "2025-09-08T02:49:13Z"
      },
      {
        "label": "bug",
        "createdAt": "2025-10-16T10:48:38Z"
      },
      {
        "label": "bug",
        "createdAt": "2025-10-18T07:43:45Z"
      },
      {
        "label": "bug",
        "createdAt": "2025-11-12T00:24:40Z"
      },
      {
        "label": "bug",
        "createdAt": "2025-11-22T14:10:23Z"
      },
      {
        "label": "bug",
        "createdAt": "2025-12-09T04:33:18Z"
      },
      {
        "label": "bug",
        "createdAt": "2025-12-14T00:40:57Z"
      },
      {
        "label": "bug",
        "createdAt": "2026-01-18T02:02:21Z"
      }
    ],
    "closedIssues": [
      {
        "originalLabel": "bug",
        "reason": "completed",
        "createdAt": "2024-04-18T09:54:12Z",
        "closedAt": "2024-04-21T08:57:49Z"
      },
      {
        "originalLabel": "bug",
        "reason": "completed",
        "createdAt": "2024-04-18T11:31:53Z",
        "closedAt": "2024-04-19T01:06:33Z"
      },
      {
        "originalLabel": "feature_request",
        "reason": "completed",
        "createdAt": "2024-04-21T08:32:41Z",
        "closedAt": "2024-04-29T08:09:47Z"
      },
      {
        "originalLabel": "feature_request",
        "reason": "completed",
        "createdAt": "2024-04-21T08:42:04Z",
        "closedAt": "2024-04-29T08:09:30Z"
      },
      {
        "originalLabel": "bug",
        "reason": "completed",
        "createdAt": "2024-04-25T02:09:54Z",
        "closedAt": "2024-04-25T06:56:13Z"
      },
      {
        "originalLabel": "bug",
        "reason": "completed",
        "createdAt": "2024-04-30T13:47:09Z",
        "closedAt": "2024-05-04T08:26:35Z"
      },
      {
        "originalLabel": "bug",
        "reason": "completed",
        "createdAt": "2024-04-30T18:05:19Z",
        "closedAt": "2024-05-26T07:04:35Z"
      },
      {
        "originalLabel": "bug",
        "reason": "completed",
        "createdAt": "2024-05-01T01:49:10Z",
        "closedAt": "2024-06-04T11:03:19Z"
      },
      {
        "originalLabel": "bug",
        "reason": "completed",
        "createdAt": "2024-05-01T04:39:15Z",
        "closedAt": "2024-05-04T08:37:58Z"
      },
      {
        "originalLabel": "bug",
        "reason": "completed",
        "createdAt": "2024-05-11T15:45:30Z",
        "closedAt": "2024-05-13T04:47:56Z"
      },
      {
        "originalLabel": "bug",
        "reason": "completed",
        "createdAt": "2024-05-14T19:38:10Z",
        "closedAt": "2024-10-12T08:46:31Z"
      },
      {
        "originalLabel": "bug",
        "reason": "completed",
        "createdAt": "2024-05-15T05:01:11Z",
        "closedAt": "2024-05-16T08:53:43Z"
      },
      {
        "originalLabel": "bug",
        "reason": "completed",
        "createdAt": "2024-05-15T05:22:21Z",
        "closedAt": "2024-05-16T09:05:39Z"
      },
      {
        "originalLabel": "bug",
        "reason": "completed",
        "createdAt": "2024-05-15T06:56:54Z",
        "closedAt": "2024-05-16T08:54:03Z"
      },
      {
        "originalLabel": "bug",
        "reason": "completed",
        "createdAt": "2024-05-17T10:23:19Z",
        "closedAt": "2024-05-18T14:29:04Z"
      },
      {
        "originalLabel": "bug",
        "reason": "completed",
        "createdAt": "2024-05-17T12:34:12Z",
        "closedAt": "2024-07-10T09:52:56Z"
      },
      {
        "originalLabel": "bug",
        "reason": "completed",
        "createdAt": "2024-05-26T10:25:57Z",
        "closedAt": "2024-06-28T07:44:51Z"
      },
      {
        "originalLabel": "bug",
        "reason": "completed",
        "createdAt": "2024-05-26T21:25:36Z",
        "closedAt": "2024-06-11T12:38:47Z"
      },
      {
        "originalLabel": "bug",
        "reason": "completed",
        "createdAt": "2024-05-27T04:22:07Z",
        "closedAt": "2024-06-01T09:02:09Z"
      },
      {
        "originalLabel": "bug",
        "reason": "completed",
        "createdAt": "2024-05-27T05:58:51Z",
        "closedAt": "2024-05-27T08:57:52Z"
      },
      {
        "originalLabel": "bug",
        "reason": "completed",
        "createdAt": "2024-05-27T06:11:57Z",
        "closedAt": "2024-05-27T08:21:48Z"
      },
      {
        "originalLabel": "bug",
        "reason": "completed",
        "createdAt": "2024-05-27T08:27:52Z",
        "closedAt": "2024-06-12T09:33:15Z"
      },
      {
        "originalLabel": "bug",
        "reason": "completed",
        "createdAt": "2024-06-02T15:10:15Z",
        "closedAt": "2024-06-04T11:03:45Z"
      },
      {
        "originalLabel": "bug",
        "reason": "completed",
        "createdAt": "2024-06-23T03:06:15Z",
        "closedAt": "2024-06-28T07:43:53Z"
      },
      {
        "originalLabel": "bug",
        "reason": "completed",
        "createdAt": "2024-07-27T07:01:21Z",
        "closedAt": "2024-07-27T13:58:03Z"
      },
      {
        "originalLabel": "bug",
        "reason": "completed",
        "createdAt": "2024-09-07T01:36:52Z",
        "closedAt": "2024-09-07T14:07:30Z"
      },
      {
        "originalLabel": "bug",
        "reason": "completed",
        "createdAt": "2024-09-09T15:17:05Z",
        "closedAt": "2024-09-09T23:17:03Z"
      },
      {
        "originalLabel": "bug",
        "reason": "completed",
        "createdAt": "2024-10-16T01:54:03Z",
        "closedAt": "2024-10-16T02:53:43Z"
      },
      {
        "originalLabel": "bug",
        "reason": "completed",
        "createdAt": "2024-10-23T08:44:23Z",
        "closedAt": "2024-10-30T02:42:14Z"
      },
      {
        "originalLabel": "bug",
        "reason": "completed",
        "createdAt": "2024-10-29T06:31:52Z",
        "closedAt": "2024-11-02T09:54:32Z"
      },
      {
        "originalLabel": "bug",
        "reason": "completed",
        "createdAt": "2024-10-31T03:53:13Z",
        "closedAt": "2024-11-18T07:36:13Z"
      },
      {
        "originalLabel": "bug",
        "reason": "completed",
        "createdAt": "2024-10-31T08:54:32Z",
        "closedAt": "2024-12-01T07:04:35Z"
      },
      {
        "originalLabel": "bug",
        "reason": "completed",
        "createdAt": "2024-11-18T07:30:33Z",
        "closedAt": "2024-12-01T07:05:13Z"
      },
      {
        "originalLabel": "bug",
        "reason": "completed",
        "createdAt": "2024-12-01T01:47:39Z",
        "closedAt": "2024-12-01T07:42:52Z"
      },
      {
        "originalLabel": "bug",
        "reason": "completed",
        "createdAt": "2024-12-06T14:27:06Z",
        "closedAt": "2024-12-10T02:20:35Z"
      },
      {
        "originalLabel": "bug",
        "reason": "completed",
        "createdAt": "2024-12-11T17:09:06Z",
        "closedAt": "2024-12-16T07:30:57Z"
      },
      {
        "originalLabel": "bug",
        "reason": "completed",
        "createdAt": "2025-01-05T04:19:11Z",
        "closedAt": "2025-01-20T12:09:56Z"
      },
      {
        "originalLabel": "bug",
        "reason": "completed",
        "createdAt": "2025-02-05T04:28:52Z",
        "closedAt": "2025-02-05T10:04:02Z"
      },
      {
        "originalLabel": "bug",
        "reason": "completed",
        "createdAt": "2025-02-05T13:32:33Z",
        "closedAt": "2025-02-07T09:00:56Z"
      },
      {
        "originalLabel": "bug",
        "reason": "completed",
        "createdAt": "2025-02-10T01:55:25Z",
        "closedAt": "2025-02-10T03:58:32Z"
      },
      {
        "originalLabel": "bug",
        "reason": "completed",
        "createdAt": "2025-02-19T10:55:47Z",
        "closedAt": "2025-02-26T07:46:12Z"
      },
      {
        "originalLabel": "bug",
        "reason": "completed",
        "createdAt": "2025-03-16T09:06:56Z",
        "closedAt": "2025-04-30T04:38:18Z"
      },
      {
        "originalLabel": "bug",
        "reason": "completed",
        "createdAt": "2025-03-25T11:16:22Z",
        "closedAt": "2025-03-26T11:13:59Z"
      },
      {
        "originalLabel": "bug",
        "reason": "completed",
        "createdAt": "2025-04-10T14:44:22Z",
        "closedAt": "2025-04-12T14:22:32Z"
      },
      {
        "originalLabel": "bug",
        "reason": "completed",
        "createdAt": "2025-05-29T03:26:53Z",
        "closedAt": "2025-09-29T02:26:36Z"
      },
      {
        "originalLabel": "bug",
        "reason": "completed",
        "createdAt": "2025-08-25T15:06:26Z",
        "closedAt": "2025-09-30T05:45:45Z"
      },
      {
        "originalLabel": "bug",
        "reason": "completed",
        "createdAt": "2025-08-28T01:36:59Z",
        "closedAt": "2025-10-04T03:34:50Z"
      },
      {
        "originalLabel": "bug",
        "reason": "completed",
        "createdAt": "2025-10-03T14:19:37Z",
        "closedAt": "2025-10-09T06:23:02Z"
      },
      {
        "originalLabel": "bug",
        "reason": "completed",
        "createdAt": "2025-10-27T08:45:52Z",
        "closedAt": "2025-10-28T10:35:49Z"
      },
      {
        "originalLabel": "bug",
        "reason": "completed",
        "createdAt": "2025-12-02T00:48:10Z",
        "closedAt": "2025-12-05T09:46:53Z"
      },
      {
        "originalLabel": "bug",
        "reason": "completed",
        "createdAt": "2025-12-07T11:56:34Z",
        "closedAt": "2025-12-07T12:45:55Z"
      },
      {
        "originalLabel": "bug",
        "reason": "completed",
        "createdAt": "2026-02-25T14:39:08Z",
        "closedAt": "2026-02-26T05:10:02Z"
      }
    ],
    "openPRs": [],
    "closedPRs": [
      {
        "createdAt": "2025-10-14T09:10:50Z",
        "closedAt": "2025-10-14T09:31:14Z"
      }
    ],
    "mergedPRs": [
      {
        "createdAt": "2025-10-16T06:33:19Z",
        "mergedAt": "2025-10-16T06:35:53Z"
      }
    ]
  },
  "now": "2026-03-04T02:21:04.175Z"
}